{"tools/22":{"draw-rectangle.png":{"h":"32","w":"32"}},"stock/24":{"stock_person.png":{"h":"22","w":"22"}},"actions/16":{"object-merge.png":{"h":"32","w":"32"},"image-red-eye.png":{"h":"32","w":"32"},"distribute-horizontal-left-symbolic.png":{"h":"32","w":"32"},"image-red-eye-symbolic.png":{"h":"32","w":"32"},"object-merge-symbolic.png":{"h":"32","w":"32"},"distribute-horizontal-left.png":{"h":"32","w":"32"}},"emblems/24":{"emblem-colors-orange.png":{"h":"16","w":"16"},"emblem-colors-green.png":{"h":"16","w":"16"},"emblem-colors-yellow.png":{"h":"16","w":"16"},"emblem-colors-violet.png":{"h":"16","w":"16"},"emblem-colors-red.png":{"h":"16","w":"16"},"emblem-colors-grey.png":{"h":"16","w":"16"},"emblem-colors-blue.png":{"h":"16","w":"16"},"emblem-colors-brown.png":{"h":"16","w":"16"},"emblem-colors-white.png":{"h":"16","w":"16"}},"apps/48":{"gnomine.png":{"h":"32","w":"32"},"force-exit.png":{"h":"48","w":"39"},"xfce4-systray.png":{"h":"48","w":"47"},"smuxi-frontend-gnome.png":{"h":"48","w":"45"},"postscript-viewer.png":{"h":"48","w":"47"},"gnome-nettool.png":{"h":"48","w":"34"},"facebook.png":{"h":"48","w":"47"},"fusion-icon.png":{"h":"41","w":"48"},"chrome-boeajhmfdjldchidhphikilcgdacljfm-Default.png":{"h":"48","w":"47"},"taskbar.png":{"h":"48","w":"43"},"xfburn.png":{"h":"32","w":"32"},"plugin-scale.png":{"h":"48","w":"47"},"audio-tag-tool.png":{"h":"37","w":"48"},"xfce4-taskbar.png":{"h":"48","w":"43"},"k3b.png":{"h":"32","w":"32"},"easytag.png":{"h":"37","w":"48"},"stock_xfburn.png":{"h":"32","w":"32"},"brasero.png":{"h":"32","w":"32"},"gnome-power-statistics.png":{"h":"48","w":"30"},"gnome-panel-window-list.png":{"h":"48","w":"43"},"mate-netspeed-applet.png":{"h":"48","w":"34"},"midori.png":{"h":"48","w":"47"},"hexchat.png":{"h":"48","w":"45"},"zenmap.png":{"h":"48","w":"34"},"usb-creator.png":{"h":"48","w":"47"},"ccsm.png":{"h":"41","w":"48"},"xfce4-splash.png":{"h":"48","w":"41"},"gnome-panel-notification-area.png":{"h":"48","w":"47"},"gnome-panel-force-quit.png":{"h":"48","w":"39"},"xchat.png":{"h":"48","w":"45"},"usb-creator-gtk.png":{"h":"48","w":"47"},"nautilus-cd-burner.png":{"h":"32","w":"32"},"xchat-gnome.png":{"h":"48","w":"45"},"im-facebook.png":{"h":"48","w":"47"},"EasyTAG_icon.png":{"h":"37","w":"48"},"org.xfce.xfburn.png":{"h":"32","w":"32"},"simple-ccsm.png":{"h":"41","w":"48"},"gnome-networktool.png":{"h":"48","w":"34"},"application-community.png":{"h":"48","w":"47"},"youtube.png":{"h":"48","w":"47"},"invest-applet.png":{"h":"46","w":"48"},"gnome-mines.png":{"h":"32","w":"32"},"chrome-blpcfgokakmgnkcojhhkbfbldkacnbeo-Default.png":{"h":"48","w":"47"},"org.xfce.panel.launcher.png":{"h":"44","w":"48"},"checkbox.png":{"h":"48","w":"47"},"xchat-mini.png":{"h":"48","w":"45"}},"status/48":{"xchat-panel.png":{"h":"48","w":"45"},"notification-message-im.png":{"h":"48","w":"47"}},"actions/scalable":{"list-add.svg":{"h":"128","w":"128"},"gtk-leave-fullscreen.svg":{"h":"128","w":"128"},"gnome-stock-mail-snd.png":{"h":"128","w":"128"},"stock_mail-send.png":{"h":"128","w":"128"},"mail-mark-important.svg":{"h":"128","w":"128"},"reload_all_tabs.svg":{"h":"128","w":"128"},"stock_media-rew.svg":{"h":"128","w":"128"},"player_pause.svg":{"h":"128","w":"128"},"media-seek-backward-symbolic.svg":{"h":"128","w":"128"},"jockey-proprietary.svg":{"h":"128","w":"128"},"gtk-apply-symbolic.svg":{"h":"128","w":"128"},"edit-find-symbolic.svg":{"h":"128","w":"128"},"format-text-bold.svg":{"h":"128","w":"128"},"stock_bottom.svg":{"h":"128","w":"128"},"go-left-symbolic.svg":{"h":"128","w":"128"},"draw-arrow-forward.svg":{"h":"128","w":"128"},"gnome-stock-text-unindent.svg":{"h":"128","w":"128"},"document-new.svg":{"h":"128","w":"128"},"help.svg":{"h":"128","w":"128"},"mail-reply-all-symbolic.svg":{"h":"128","w":"128"},"edit-duplicate.svg":{"h":"128","w":"128"},"gtk-zoom-out.svg":{"h":"128","w":"128"},"call-stop.svg":{"h":"128","w":"128"},"stock_cut.svg":{"h":"128","w":"128"},"format-text-bold-symbolic.svg":{"h":"128","w":"128"},"gtk-new.svg":{"h":"128","w":"128"},"help-about.svg":{"h":"128","w":"128"},"stock_text_left.svg":{"h":"128","w":"128"},"edit-paste.svg":{"h":"128","w":"128"},"media-playback-pause.svg":{"h":"128","w":"128"},"player_rew.svg":{"h":"128","w":"128"},"gtk-tab-new.svg":{"h":"128","w":"128"},"go-previous.svg":{"h":"128","w":"128"},"mail-reply-all.svg":{"h":"128","w":"128"},"blueman-untrust.svg":{"h":"128","w":"128"},"gtk-redo-ltr.svg":{"h":"128","w":"128"},"gtk-media-forward-ltr.svg":{"h":"128","w":"128"},"bookmark_list_add.svg":{"h":"128","w":"128"},"edit-clear.svg":{"h":"128","w":"128"},"view-sort-descending.svg":{"h":"128","w":"128"},"go-next-symbolic-rtl.svg":{"h":"128","w":"128"},"edit-delete.svg":{"h":"128","w":"128"},"gtk-find-and-replace.svg":{"h":"128","w":"128"},"document-save-symbolic.svg":{"h":"128","w":"128"},"gtk-delete.svg":{"h":"128","w":"128"},"zoom-original-symbolic.symbolic.svg":{"h":"128","w":"128"},"leftjust.svg":{"h":"128","w":"128"},"view-restore.svg":{"h":"128","w":"128"},"mail-mark-important-symbolic.svg":{"h":"128","w":"128"},"text_italic.svg":{"h":"128","w":"128"},"format-text-strikethrough-symbolic.svg":{"h":"128","w":"128"},"appointment-new.svg":{"h":"128","w":"128"},"window_nofullscreen.svg":{"h":"128","w":"128"},"stock_zoom-page.svg":{"h":"128","w":"128"},"collection-rescan-amarok.svg":{"h":"128","w":"128"},"player_record.svg":{"h":"128","w":"128"},"bookmark_add.svg":{"h":"128","w":"128"},"mail-reply-sender.svg":{"h":"128","w":"128"},"window_new.svg":{"h":"128","w":"128"},"contact-new.svg":{"h":"128","w":"128"},"stock_sent-mail.svg":{"h":"128","w":"128"},"edit-find-replace-symbolic.svg":{"h":"128","w":"128"},"filesaveas.svg":{"h":"128","w":"128"},"stock_copy.svg":{"h":"128","w":"128"},"add.svg":{"h":"128","w":"128"},"stock_save.svg":{"h":"128","w":"128"},"document-revert.svg":{"h":"128","w":"128"},"stock_search.svg":{"h":"128","w":"128"},"stock_media-play.svg":{"h":"128","w":"128"},"edit-add.svg":{"h":"128","w":"128"},"document-import.svg":{"h":"128","w":"128"},"gtk-media-forward-rtl.svg":{"h":"128","w":"128"},"edit-copy-symbolic.svg":{"h":"128","w":"128"},"document-export.svg":{"h":"128","w":"128"},"gtk-cancel.svg":{"h":"128","w":"128"},"edit-paste-symbolic.svg":{"h":"128","w":"128"},"stock_file-properites.svg":{"h":"128","w":"128"},"fileprint.svg":{"h":"128","w":"128"},"stock_mail-compose.svg":{"h":"128","w":"128"},"stock_text_underlined.svg":{"h":"128","w":"128"},"gtk-no.svg":{"h":"128","w":"128"},"gtk-add.svg":{"h":"128","w":"128"},"gtk-media-previous-ltr.svg":{"h":"128","w":"128"},"edit-find.svg":{"h":"128","w":"128"},"system-run.svg":{"h":"128","w":"128"},"gtk-stop.svg":{"h":"128","w":"128"},"mail-send.png":{"h":"128","w":"128"},"player_fwd.svg":{"h":"128","w":"128"},"zoom-out.svg":{"h":"128","w":"128"},"document-print-preview.svg":{"h":"128","w":"128"},"viewmag-.svg":{"h":"128","w":"128"},"action-unavailable.svg":{"h":"128","w":"128"},"draw-arrow-back.svg":{"h":"128","w":"128"},"gnome-stock-mail-fwd.svg":{"h":"128","w":"128"},"edit-clear-all.svg":{"h":"128","w":"128"},"go-first.svg":{"h":"128","w":"128"},"gtk-add-symbolic.svg":{"h":"128","w":"128"},"stock_text_unindent.svg":{"h":"128","w":"128"},"gtk-strikethrough.svg":{"h":"128","w":"128"},"gnome-app-install-star.svg":{"h":"128","w":"128"},"tab-new.svg":{"h":"128","w":"128"},"view-window-new.svg":{"h":"128","w":"128"},"stock_help-add-bookmark.svg":{"h":"128","w":"128"},"filefind.svg":{"h":"128","w":"128"},"go-next.svg":{"h":"128","w":"128"},"view-fullscreen-symbolic.svg":{"h":"128","w":"128"},"gtk-undo-ltr.svg":{"h":"128","w":"128"},"format-text-strikethrough.svg":{"h":"128","w":"128"},"folder_new.svg":{"h":"128","w":"128"},"stock_new-address-book.svg":{"h":"128","w":"128"},"gtk-media-previous-rtl.svg":{"h":"128","w":"128"},"media-import-audio-cd-symbolic.svg":{"h":"128","w":"128"},"format-justify-center-symbolic.svg":{"h":"128","w":"128"},"document-print-preview-symbolic.svg":{"h":"128","w":"128"},"centrejust.svg":{"h":"128","w":"128"},"gtk-save-as.svg":{"h":"128","w":"128"},"system-run-symbolic.svg":{"h":"128","w":"128"},"stock_media-fwd.svg":{"h":"128","w":"128"},"bottom.svg":{"h":"128","w":"128"},"insert-image.svg":{"h":"128","w":"128"},"format-text-italic.svg":{"h":"128","w":"128"},"insert-link.svg":{"h":"128","w":"128"},"document-export-symbolic.svg":{"h":"128","w":"128"},"vm-create.svg":{"h":"128","w":"128"},"forward.svg":{"h":"128","w":"128"},"arrow-up.svg":{"h":"128","w":"128"},"stock_down.svg":{"h":"128","w":"128"},"system-restart.svg":{"h":"128","w":"128"},"go-top.svg":{"h":"128","w":"128"},"exit.svg":{"h":"96","w":"96"},"down.svg":{"h":"128","w":"128"},"document-new-symbolic.svg":{"h":"128","w":"128"},"finish.svg":{"h":"128","w":"128"},"arrow-right.svg":{"h":"128","w":"128"},"mail-mark-important.png":{"h":"128","w":"128"},"view-refresh.svg":{"h":"128","w":"128"},"stock_save-as.svg":{"h":"128","w":"128"},"system-lock-screen.svg":{"h":"128","w":"128"},"go-last-symbolic.svg":{"h":"128","w":"128"},"edit-select-all.svg":{"h":"128","w":"128"},"gtk-justify-fill.svg":{"h":"128","w":"128"},"address-book-new.svg":{"h":"128","w":"128"},"tag-new.svg":{"h":"128","w":"128"},"media-playback-stop.svg":{"h":"128","w":"128"},"stock_redo.svg":{"h":"128","w":"128"},"gnome-session-reboot.svg":{"h":"128","w":"128"},"system-restart_old.svg":{"h":"128","w":"128"},"process-stop.svg":{"h":"128","w":"128"},"redo.svg":{"h":"128","w":"128"},"stock_folder-properties.svg":{"h":"128","w":"128"},"view-fullscreen.svg":{"h":"128","w":"128"},"media-seek-backward.svg":{"h":"128","w":"128"},"stock_media-next.svg":{"h":"128","w":"128"},"zoom-fit-best-symbolic.svg":{"h":"128","w":"128"},"gtk-edit-symbolic.svg":{"h":"128","w":"128"},"gtk-goto-bottom.svg":{"h":"128","w":"128"},"xfsm-reboot.svg":{"h":"128","w":"128"},"stock_new-text.svg":{"h":"128","w":"128"},"stock_last.svg":{"h":"128","w":"128"},"gtk-find.svg":{"h":"128","w":"128"},"media-skip-forward.svg":{"h":"128","w":"128"},"filequickprint.svg":{"h":"128","w":"128"},"gtk-jump-to-rtl.svg":{"h":"128","w":"128"},"gtk-paste.svg":{"h":"128","w":"128"},"format-justify-right-symbolic.svg":{"h":"128","w":"128"},"mail-mark-important-symbolic.png":{"h":"128","w":"128"},"stock_new-window.svg":{"h":"128","w":"128"},"media-record-symbolic.svg":{"h":"128","w":"128"},"fileopen.svg":{"h":"128","w":"128"},"go-left.svg":{"h":"128","w":"128"},"stock_paste.svg":{"h":"128","w":"128"},"insert-object.svg":{"h":"128","w":"128"},"object-inverse.svg":{"h":"128","w":"128"},"gtk-new-tab.svg":{"h":"128","w":"128"},"media-playback-pause-symbolic.svg":{"h":"128","w":"128"},"zoom-fit-best.svg":{"h":"128","w":"128"},"media-record.svg":{"h":"128","w":"128"},"go-right.svg":{"h":"128","w":"128"},"document-page-setup.svg":{"h":"128","w":"128"},"vm-settings.svg":{"h":"128","w":"128"},"gtk-media-rewind-ltr.svg":{"h":"128","w":"128"},"filesave.svg":{"h":"128","w":"128"},"rightjust.svg":{"h":"128","w":"128"},"gtk-revert-to-saved-rtl.svg":{"h":"128","w":"128"},"stock_properties.svg":{"h":"128","w":"128"},"gtk-sort-ascending.svg":{"h":"128","w":"128"},"gtk-jump-to-ltr.svg":{"h":"128","w":"128"},"gnome-lockscreen.svg":{"h":"128","w":"128"},"stock_sent-mail.png":{"h":"128","w":"128"},"gtk-print-report.svg":{"h":"128","w":"128"},"go-next-rtl.svg":{"h":"128","w":"128"},"system-restart-panel.svg":{"h":"128","w":"128"},"appointment-symbolic.svg":{"h":"128","w":"128"},"stock_new-appointment.svg":{"h":"128","w":"128"},"up.svg":{"h":"128","w":"128"},"stock_media-stop.svg":{"h":"128","w":"128"},"stock_new-tab.svg":{"h":"128","w":"128"},"gnome-stock-mail-rpl.svg":{"h":"128","w":"128"},"view-refresh-symbolic.svg":{"h":"128","w":"128"},"go-jump.svg":{"h":"128","w":"128"},"media-seek-forward.svg":{"h":"128","w":"128"},"document-save-as.svg":{"h":"128","w":"128"},"folder-recent.svg":{"h":"128","w":"128"},"arrow-down.svg":{"h":"128","w":"128"},"xfce-system-lock.svg":{"h":"128","w":"128"},"gtk-revert-to-saved-ltr.svg":{"h":"128","w":"128"},"org.xfce.about.svg":{"h":"128","w":"128"},"gtk-go-back-ltr.svg":{"h":"128","w":"128"},"format-text-italic-symbolic.svg":{"h":"128","w":"128"},"edit-clear-symbolic.svg":{"h":"128","w":"128"},"system-reboot.svg":{"h":"128","w":"128"},"blueman-untrust-symbolic.svg":{"h":"128","w":"128"},"go-bottom.svg":{"h":"128","w":"128"},"document-properties.svg":{"h":"128","w":"128"},"gtk-unindent-rtl.svg":{"h":"128","w":"128"},"edit-copy.svg":{"h":"128","w":"128"},"document-send-symbolic.svg":{"h":"128","w":"128"},"tools-check-spelling.svg":{"h":"128","w":"128"},"reload3.svg":{"h":"128","w":"128"},"editcopy.svg":{"h":"128","w":"128"},"text_under.svg":{"h":"128","w":"128"},"gtk-media-rewind-rtl.svg":{"h":"128","w":"128"},"revert.svg":{"h":"128","w":"128"},"stock_undo.svg":{"h":"128","w":"128"},"tag-new-symbolic.svg":{"h":"128","w":"128"},"media-skip-backward-rtl.svg":{"h":"128","w":"128"},"file_new.svg":{"h":"128","w":"128"},"mail-send-receive-symbolic.svg":{"h":"128","w":"128"},"reload_page.svg":{"h":"128","w":"128"},"document-send.svg":{"h":"128","w":"128"},"undo.svg":{"h":"128","w":"128"},"stock_select-all.svg":{"h":"128","w":"128"},"object-rotate-left.svg":{"h":"128","w":"128"},"gtk-unindent-ltr.svg":{"h":"128","w":"128"},"edit-correct.svg":{"h":"128","w":"128"},"stock_text_right.svg":{"h":"128","w":"128"},"vm-power-on.svg":{"h":"128","w":"128"},"search.svg":{"h":"128","w":"128"},"document-properties-symbolic.svg":{"h":"128","w":"128"},"view-restore-symbolic.svg":{"h":"128","w":"128"},"editdelete.svg":{"h":"128","w":"128"},"appointment-new-symbolic.svg":{"h":"128","w":"128"},"object-flip-horizontal-symbolic.svg":{"h":"128","w":"128"},"gtk-zoom-in.svg":{"h":"128","w":"128"},"address-book-new-symbolic.svg":{"h":"128","w":"128"},"gtk-clear.svg":{"h":"128","w":"128"},"application-exit.svg":{"h":"96","w":"96"},"format-justify-center.svg":{"h":"128","w":"128"},"stock_first.svg":{"h":"128","w":"128"},"gtk-go-back-rtl.svg":{"h":"128","w":"128"},"edit-undo-rtl.svg":{"h":"128","w":"128"},"edit-cut.svg":{"h":"128","w":"128"},"mail_new.svg":{"h":"128","w":"128"},"view-window_new.svg":{"h":"128","w":"128"},"go-top-symbolic.svg":{"h":"128","w":"128"},"edit-redo.svg":{"h":"128","w":"128"},"stock_top.svg":{"h":"128","w":"128"},"zoom-original.svg":{"h":"128","w":"128"},"folder-new-symbolic.svg":{"h":"128","w":"128"},"mail_reply.svg":{"h":"128","w":"128"},"cm_refresh.svg":{"h":"128","w":"128"},"stock_fullscreen.svg":{"h":"128","w":"128"},"stock_text_justify.svg":{"h":"128","w":"128"},"stock_zoom-in.svg":{"h":"128","w":"128"},"system-restart-symbolic.svg":{"h":"128","w":"128"},"mail-mark-unread.svg":{"h":"128","w":"128"},"gtk-cut.svg":{"h":"128","w":"128"},"gtk-apply.svg":{"h":"128","w":"128"},"appointment.svg":{"h":"128","w":"128"},"edit-select-all-symbolic.svg":{"h":"128","w":"128"},"1uparrow.svg":{"h":"128","w":"128"},"fm-new.svg":{"h":"128","w":"128"},"mail-send-receive.svg":{"h":"128","w":"128"},"vm-restart.svg":{"h":"128","w":"128"},"edit-find-replace.svg":{"h":"128","w":"128"},"centerjust.svg":{"h":"128","w":"128"},"format-text-direction-rtl-symbolic.svg":{"h":"128","w":"128"},"gtk-print-error.svg":{"h":"128","w":"128"},"gtk-media-pause.svg":{"h":"128","w":"128"},"format-justify-fill.svg":{"h":"128","w":"128"},"application-add-symbolic.svg":{"h":"128","w":"128"},"gtk-indent-ltr.svg":{"h":"128","w":"128"},"gtk-goto-first-ltr.svg":{"h":"128","w":"128"},"previous.svg":{"h":"128","w":"128"},"stock_mail-send-receive.svg":{"h":"128","w":"128"},"gtk-goto-top.svg":{"h":"128","w":"128"},"gtk-sort-descending.svg":{"h":"128","w":"128"},"format-text-underline.svg":{"h":"128","w":"128"},"player_play.svg":{"h":"128","w":"128"},"mail_replyall.svg":{"h":"128","w":"128"},"stock_zoom-1.svg":{"h":"128","w":"128"},"stock_add-bookmark.svg":{"h":"128","w":"128"},"gtk-goto-up.svg":{"h":"128","w":"128"},"stock_spellcheck.svg":{"h":"128","w":"128"},"gtk-open.svg":{"h":"128","w":"128"},"gtk-go-down.svg":{"h":"128","w":"128"},"gtk-quit.svg":{"h":"96","w":"96"},"gtk-copy.svg":{"h":"128","w":"128"},"gtk-print-warning.svg":{"h":"128","w":"128"},"tab_new.svg":{"h":"128","w":"128"},"stock_filters-invert.svg":{"h":"128","w":"128"},"gtk-execute.svg":{"h":"128","w":"128"},"gtk-save.svg":{"h":"128","w":"128"},"media-import-audio-cd.svg":{"h":"128","w":"128"},"stock_leave-fullscreen.svg":{"h":"128","w":"128"},"blueman-send-file.svg":{"h":"128","w":"128"},"media-eject.svg":{"h":"128","w":"128"},"stock_text_indent.svg":{"h":"128","w":"128"},"gtk-indent-rtl.svg":{"h":"128","w":"128"},"stock_mail-reply-to-all.svg":{"h":"128","w":"128"},"list-add-symbolic.symbolic.svg":{"h":"128","w":"128"},"gtk-goto-first-rtl.svg":{"h":"128","w":"128"},"mail_send.svg":{"h":"128","w":"128"},"locationbar-erase.svg":{"h":"128","w":"128"},"mail-forward-symbolic.svg":{"h":"128","w":"128"},"gtk-print-paused.svg":{"h":"128","w":"128"},"zoom-in.svg":{"h":"128","w":"128"},"filenew.svg":{"h":"128","w":"128"},"gtk-refresh.svg":{"h":"128","w":"128"},"editpaste.svg":{"h":"128","w":"128"},"stock_right.svg":{"h":"128","w":"128"},"start.svg":{"h":"128","w":"128"},"go-up.svg":{"h":"128","w":"128"},"go-down-symbolic.svg":{"h":"128","w":"128"},"media-eject-symbolic.svg":{"h":"128","w":"128"},"stock_text_center.svg":{"h":"128","w":"128"},"zoom-in-symbolic.svg":{"h":"128","w":"128"},"rhythmbox-set-star.svg":{"h":"128","w":"128"},"gtk-italic.svg":{"h":"128","w":"128"},"bonobo-component-browser.svg":{"h":"128","w":"128"},"gtk-go-bottom.svg":{"h":"128","w":"128"},"next.svg":{"h":"128","w":"128"},"stock_media-rec.svg":{"h":"128","w":"128"},"lc_alignright.svg":{"h":"128","w":"128"},"history-view.svg":{"h":"128","w":"128"},"vmware-checkpoint-next.svg":{"h":"128","w":"128"},"object-rotate-right.svg":{"h":"128","w":"128"},"stock_new-bcard.svg":{"h":"128","w":"128"},"gtk-zoom-100.svg":{"h":"128","w":"128"},"go-bottom-symbolic.svg":{"h":"128","w":"128"},"gtk-spell-check.svg":{"h":"128","w":"128"},"go-previous-rtl-symbolic.svg":{"h":"128","w":"128"},"exaile-pause.svg":{"h":"128","w":"128"},"stock_print-preview.svg":{"h":"128","w":"128"},"player_eject.svg":{"h":"128","w":"128"},"stock_refresh.svg":{"h":"128","w":"128"},"call-start.svg":{"h":"128","w":"128"},"go-jump-symbolic.svg":{"h":"128","w":"128"},"player_end.svg":{"h":"128","w":"128"},"panel-searchtool.svg":{"h":"128","w":"128"},"history.svg":{"h":"128","w":"128"},"1downarrow.svg":{"h":"128","w":"128"},"insert-text.svg":{"h":"128","w":"128"},"document-print.svg":{"h":"128","w":"128"},"vm-suspend.svg":{"h":"128","w":"128"},"mail-reply-sender-symbolic.svg":{"h":"128","w":"128"},"format-justify-right.svg":{"h":"128","w":"128"},"object-flip-vertical-symbolic.svg":{"h":"128","w":"128"},"viewmag1.svg":{"h":"128","w":"128"},"browser-download.svg":{"h":"128","w":"128"},"stock_text_bold.svg":{"h":"128","w":"128"},"gtk-properties.svg":{"h":"128","w":"128"},"stock_stop.svg":{"h":"128","w":"128"},"stock_search-and-replace.svg":{"h":"128","w":"128"},"media-skip-forward-symbolic.svg":{"h":"128","w":"128"},"gtk-media-record.svg":{"h":"128","w":"128"},"document-save-as-symbolic.svg":{"h":"128","w":"128"},"gtk-justify-left.svg":{"h":"128","w":"128"},"view-sort-ascending.svg":{"h":"128","w":"128"},"gtk-media-stop.svg":{"h":"128","w":"128"},"bookmark-new.svg":{"h":"128","w":"128"},"stop.svg":{"h":"128","w":"128"},"object-inverse-symbolic.svg":{"h":"128","w":"128"},"go-first-symbolic.svg":{"h":"128","w":"128"},"stock_media-pause.svg":{"h":"128","w":"128"},"stock-refresh.svg":{"h":"128","w":"128"},"stock_new-dir.svg":{"h":"128","w":"128"},"gtk-go-forward-ltr.svg":{"h":"128","w":"128"},"edit-undo.svg":{"h":"128","w":"128"},"gtk-about.svg":{"h":"128","w":"128"},"gtk-print-report-symbolic.svg":{"h":"128","w":"128"},"go-up-symbolic.svg":{"h":"128","w":"128"},"stock_mail-reply.svg":{"h":"128","w":"128"},"edit-undo-symbolic.svg":{"h":"128","w":"128"},"amarok_playlist_refresh.svg":{"h":"128","w":"128"},"stock_about.svg":{"h":"128","w":"128"},"bookmarks_list_add.svg":{"h":"128","w":"128"},"document-revert-symbolic.svg":{"h":"128","w":"128"},"edit-clear-all-symbolic.svg":{"h":"128","w":"128"},"gtk-media-next-rtl.svg":{"h":"128","w":"128"},"gnome-stock-text-indent.svg":{"h":"128","w":"128"},"go-previous-symbolic.svg":{"h":"128","w":"128"},"editclear.svg":{"h":"128","w":"128"},"default-document-open-recent.svg":{"h":"128","w":"128"},"gnome-stock-mail-snd.svg":{"h":"128","w":"128"},"stock_mail-send.svg":{"h":"128","w":"128"},"process-stop-symbolic.svg":{"h":"128","w":"128"},"gtk-redo.svg":{"h":"128","w":"128"},"stock_left.svg":{"h":"128","w":"128"},"format-justify-left-symbolic.svg":{"h":"128","w":"128"},"application-exit-symbolic.svg":{"h":"96","w":"96"},"dialog-apply-symbolic.svg":{"h":"128","w":"128"},"xfsm-lock.svg":{"h":"128","w":"128"},"stock_close.svg":{"h":"128","w":"128"},"text_strike.svg":{"h":"128","w":"128"},"gtk-media-next-ltr.svg":{"h":"128","w":"128"},"preview-file.svg":{"h":"128","w":"128"},"list-add-symbolic.svg":{"h":"128","w":"128"},"object-flip-vertical.svg":{"h":"128","w":"128"},"format-indent-more-rtl.svg":{"h":"128","w":"128"},"go-next-symbolic.svg":{"h":"128","w":"128"},"gtk-media-play-ltr.svg":{"h":"128","w":"128"},"gtk-go-forward-rtl.svg":{"h":"128","w":"128"},"zoom-best-fit.svg":{"h":"128","w":"128"},"stock_delete.svg":{"h":"128","w":"128"},"gnome-run.svg":{"h":"128","w":"128"},"format-indent-less.svg":{"h":"128","w":"128"},"help-faq.svg":{"h":"128","w":"128"},"player_stop.svg":{"h":"128","w":"128"},"stock_up.svg":{"h":"128","w":"128"},"reload.svg":{"h":"128","w":"128"},"default-document-open.svg":{"h":"128","w":"128"},"media-playback-start.svg":{"h":"128","w":"128"},"go-previous-symbolic-rtl.svg":{"h":"128","w":"128"},"lock.svg":{"h":"128","w":"128"},"document-open-recent.svg":{"h":"128","w":"128"},"stock_print-setup.svg":{"h":"128","w":"128"},"media-skip-backward.svg":{"h":"128","w":"128"},"format-text-direction-rtl.svg":{"h":"128","w":"128"},"gtk-justify-right.svg":{"h":"128","w":"128"},"gtk-zoom-fit.svg":{"h":"128","w":"128"},"gtk-underline.svg":{"h":"128","w":"128"},"go-down.svg":{"h":"128","w":"128"},"vm-power-off.svg":{"h":"128","w":"128"},"project-open.svg":{"h":"128","w":"128"},"window-new.svg":{"h":"128","w":"128"},"gtk-goto-last-ltr.svg":{"h":"128","w":"128"},"text_bold.svg":{"h":"128","w":"128"},"xfce-system-exit.svg":{"h":"96","w":"96"},"stock_text_italic.svg":{"h":"128","w":"128"},"1leftarrow.svg":{"h":"128","w":"128"},"back.svg":{"h":"128","w":"128"},"gtk-justify-center.svg":{"h":"128","w":"128"},"go-right-symbolic.svg":{"h":"128","w":"128"},"format-text-direction-ltr.svg":{"h":"128","w":"128"},"mail-message-new.svg":{"h":"128","w":"128"},"mail-forward.svg":{"h":"128","w":"128"},"gnome-stock-mail-new.svg":{"h":"128","w":"128"},"window_fullscreen.svg":{"h":"128","w":"128"},"mail_send.png":{"h":"128","w":"128"},"gtk-close.svg":{"h":"128","w":"128"},"vmware-manage-autostart-vms.svg":{"h":"128","w":"128"},"gtk-bold.svg":{"h":"128","w":"128"},"zoom-in-symbolic.symbolic.svg":{"h":"128","w":"128"},"color-picker.png":{"h":"512","w":"512"},"bookmark-new-symbolic.svg":{"h":"128","w":"128"},"find.svg":{"h":"128","w":"128"},"gtk-select-all.svg":{"h":"128","w":"128"},"format-text-underline-symbolic.svg":{"h":"128","w":"128"},"stock_mail-forward.svg":{"h":"128","w":"128"},"gtk-edit.svg":{"h":"128","w":"128"},"edit-add-symbolic.svg":{"h":"128","w":"128"},"vmware-checkpoint-previous.svg":{"h":"128","w":"128"},"player_start.svg":{"h":"128","w":"128"},"stock_print.svg":{"h":"128","w":"128"},"1rightarrow.svg":{"h":"128","w":"128"},"gtk-go-up.svg":{"h":"128","w":"128"},"gtk-undo.svg":{"h":"128","w":"128"},"edit-redo-symbolic.svg":{"h":"128","w":"128"},"mail-send.svg":{"h":"128","w":"128"},"arrow-left.svg":{"h":"128","w":"128"},"go-next-rtl-symbolic.svg":{"h":"128","w":"128"},"go-last.svg":{"h":"128","w":"128"},"gtk-goto-last-rtl.svg":{"h":"128","w":"128"},"tab-new-symbolic.svg":{"h":"128","w":"128"},"mail_forward.svg":{"h":"128","w":"128"},"zoom-original-symbolic.svg":{"h":"128","w":"128"},"gtk-remove.svg":{"h":"128","w":"128"},"top.svg":{"h":"128","w":"128"},"setroubleshoot_icon.svg":{"h":"128","w":"128"},"gtk-no-symbolic.svg":{"h":"128","w":"128"},"gtk-fullscreen.svg":{"h":"128","w":"128"},"stock_text-strikethrough.svg":{"h":"128","w":"128"},"gtk-print-preview.svg":{"h":"128","w":"128"},"edit-add-symbolic.symbolic.svg":{"h":"128","w":"128"},"document-open.svg":{"h":"128","w":"128"},"object-flip-horizontal.svg":{"h":"128","w":"128"},"format-text-direction-ltr-symbolic.svg":{"h":"128","w":"128"},"document-open-symbolic.svg":{"h":"128","w":"128"},"folder-new.svg":{"h":"128","w":"128"},"format-justify-left.svg":{"h":"128","w":"128"},"editcut.svg":{"h":"128","w":"128"},"stock_zoom-out.svg":{"h":"128","w":"128"},"viewmagfit.svg":{"h":"128","w":"128"},"document-save.svg":{"h":"128","w":"128"},"edit-cut-symbolic.svg":{"h":"128","w":"128"},"edit-delete-symbolic.svg":{"h":"128","w":"128"},"zoom-out-symbolic.symbolic.svg":{"h":"128","w":"128"},"mail-forward-rtl.svg":{"h":"128","w":"128"},"zoom-out-symbolic.svg":{"h":"128","w":"128"},"stock_media-prev.svg":{"h":"128","w":"128"},"invertimage.svg":{"h":"128","w":"128"},"format-indent-more.svg":{"h":"128","w":"128"},"gtk-print.svg":{"h":"128","w":"128"},"mail-mark-read.svg":{"h":"128","w":"128"},"dialog-apply.svg":{"h":"128","w":"128"},"stock-refresh2.svg":{"h":"128","w":"128"},"viewmag+.svg":{"h":"128","w":"128"},"document-print-symbolic.svg":{"h":"128","w":"128"},"window-new-symbolic.svg":{"h":"128","w":"128"}},"categories/22":{"documentation_section.png":{"h":"24","w":"24"}},"animations/48":{"pk-action-refresh-cache.svg":{"h":"48","w":"384"}},"categories/24":{"applications-multimedia.png":{"h":"21","w":"24"}},"apps/22":{"indicator-applet.png":{"h":"24","w":"24"},"org.xfce.xfburn.png":{"h":"16","w":"16"},"gnome-info.png":{"h":"24","w":"24"},"nautilus-cd-burner.png":{"h":"16","w":"16"},"stock_help-agent.png":{"h":"24","w":"24"},"brasero.png":{"h":"16","w":"16"},"mate-notification-properties.png":{"h":"24","w":"24"},"stock_view-details.png":{"h":"24","w":"24"},"xfburn.png":{"h":"16","w":"16"},"plugin-notification.png":{"h":"24","w":"24"},"stock_xfburn.png":{"h":"16","w":"16"},"gtk-info.png":{"h":"24","w":"24"},"k3b.png":{"h":"16","w":"16"}},"devices/24":{"multimedia-player.png":{"h":"24","w":"23"},"gnome-dev-battery.png":{"h":"24","w":"23"},"music-player.png":{"h":"24","w":"23"},"network-wired-symbolic.png":{"h":"24","w":"23"},"gnome-dev-wavelan.png":{"h":"24","w":"23"},"network-wireless.png":{"h":"24","w":"23"},"camera-video.png":{"h":"24","w":"23"},"gnome-dev-ipod.png":{"h":"24","w":"23"},"gnome-dev-zipdisk.png":{"h":"24","w":"23"},"joystick.png":{"h":"24","w":"23"},"media-zip.png":{"h":"24","w":"23"},"camera_unmount.png":{"h":"24","w":"23"},"ipod_mount.png":{"h":"24","w":"23"},"battery.png":{"h":"24","w":"23"},"network-wired.png":{"h":"24","w":"23"},"network-wireless-symbolic.png":{"h":"24","w":"23"},"gnome-dev-ethernet.png":{"h":"24","w":"23"},"camera-video-symbolic.png":{"h":"24","w":"23"},"media-jaz.png":{"h":"24","w":"23"},"gnome-dev-jazdisk.png":{"h":"24","w":"23"}},"apps/32":{"palm-pilot-sync":{"h":"48","w":"48"},"gksu-debian.svg":{"h":"640","w":"640"},"cs-cat-admin.svg":{"h":"640","w":"640"},"gksu-root-terminal.svg":{"h":"640","w":"640"}},"status/22":{"xfce-unknown.png":{"h":"24","w":"24"}},"animations/10":{"process-idle.svg":{"h":"16","w":"16"},"process-working.png":{"h":"100","w":"10"},"spinner.png":{"h":"100","w":"10"},"gnome-spinner.png":{"h":"100","w":"10"},"gnome-spinner-rest.svg":{"h":"16","w":"16"}},"mimes/22":{"libreoffice-oasis-text-template.png":{"h":"24","w":"24"},"libreoffice-drawing-template.png":{"h":"24","w":"24"},"application-vnd.oasis.opendocument.text-template.png":{"h":"24","w":"24"},"x-office-document-template.png":{"h":"24","w":"24"},"application-illustrator.png":{"h":"16","w":"16"},"application-vnd.oasis.opendocument.drawing-template.png":{"h":"24","w":"24"},"libreoffice-oasis-drawing-template.png":{"h":"24","w":"24"},"libreoffice-text-template.png":{"h":"24","w":"24"},"application-epub+zip.png":{"h":"16","w":"16"}},"mimes/32":{"application-x-java.png":{"h":"48","w":"48"},"gnome-mime-application-x-java.png":{"h":"48","w":"48"}},"emblems/scalable":{"emblem-documents.svg":{"h":"96","w":"96"},"emblem-colors-yellow.svg":{"h":"96","w":"96"},"emblem-nowrite.svg":{"h":"96","w":"96"},"emblem-symbolic-link.svg":{"h":"96","w":"96"},"emblem-new.svg":{"h":"96","w":"96"},"emblem-colors-violet.svg":{"h":"96","w":"96"},"emblem-colors-grey.svg":{"h":"96","w":"96"},"globe-symbolic.svg":{"h":"96","w":"96"},"emblem-colors-red.svg":{"h":"96","w":"96"},"emblem-documents-symbolic.svg":{"h":"96","w":"96"},"emblem-photos.svg":{"h":"96","w":"96"},"emblem-package.svg":{"h":"96","w":"96"},"emblem-colors-brown.svg":{"h":"96","w":"96"},"blueman-blocked-emblem.svg":{"h":"96","w":"96"},"emblem-colors-blue.svg":{"h":"96","w":"96"},"emblem-web.svg":{"h":"96","w":"96"},"emblem-favorite.svg":{"h":"96","w":"96"},"emblem-system.svg":{"h":"96","w":"96"},"emblem-urgent.svg":{"h":"96","w":"96"},"emblem-unreadable.svg":{"h":"96","w":"96"},"emblem-mail.svg":{"h":"96","w":"96"},"emblem-shared.svg":{"h":"96","w":"96"},"emblem-generic.svg":{"h":"96","w":"96"},"emblem-colors-white.svg":{"h":"96","w":"96"},"emblem-default.svg":{"h":"96","w":"96"},"emblem-noread.svg":{"h":"96","w":"96"},"emblem-important.svg":{"h":"96","w":"96"},"emblem-colors-orange.svg":{"h":"96","w":"96"},"emblem-readonly.svg":{"h":"96","w":"96"},"emblem-downloads.svg":{"h":"96","w":"96"},"emblem-colors-green.svg":{"h":"96","w":"96"},"blueman-trusted-emblem.svg":{"h":"96","w":"96"}},"apps/24":{"utilities-log-viewer.png":{"h":"24","w":"20"},"plugin-screenshot.png":{"h":"24","w":"23"},"force-exit.png":{"h":"24","w":"19"},"applets-screenshooter.png":{"h":"24","w":"23"},"smuxi-frontend-gnome.png":{"h":"24","w":"23"},"gnome-nettool.png":{"h":"24","w":"17"},"gnome-fs-bookmark-missing.png":{"h":"24","w":"19"},"im-aim.png":{"h":"24","w":"19"},"stock_delete-bookmark.png":{"h":"24","w":"19"},"logviewer.png":{"h":"24","w":"20"},"org.gnome.Screenshot.png":{"h":"24","w":"23"},"fusion-icon.png":{"h":"21","w":"24"},"timer-applet.png":{"h":"24","w":"23"},"gnome-screenshot.png":{"h":"24","w":"23"},"config-date.png":{"h":"24","w":"23"},"time-admin.png":{"h":"24","w":"23"},"audio-tag-tool.png":{"h":"19","w":"24"},"easytag.png":{"h":"19","w":"24"},"xfce4-weather.png":{"h":"24","w":"21"},"gnome-power-statistics.png":{"h":"24","w":"23"},"mate-netspeed-applet.png":{"h":"24","w":"17"},"hexchat.png":{"h":"24","w":"23"},"zenmap.png":{"h":"24","w":"17"},"clocks.png":{"h":"24","w":"23"},"org.xfce.screenshooter.png":{"h":"24","w":"23"},"org.xfce.tumbler.png":{"h":"24","w":"23"},"spectacle.png":{"h":"24","w":"23"},"ccsm.png":{"h":"21","w":"24"},"xfce4-splash.png":{"h":"24","w":"21"},"beryl-settings.png":{"h":"22","w":"24"},"im-yahoo.png":{"h":"14","w":"24"},"gnome-panel-force-quit.png":{"h":"24","w":"19"},"xchat.png":{"h":"24","w":"23"},"screengrab.png":{"h":"24","w":"23"},"blueradio.png":{"h":"24","w":"18"},"xchat-gnome.png":{"h":"24","w":"23"},"EasyTAG_icon.png":{"h":"19","w":"24"},"simple-ccsm.png":{"h":"21","w":"24"},"gnome-networktool.png":{"h":"24","w":"17"},"screenie-qt.png":{"h":"24","w":"23"},"ksnapshot.png":{"h":"24","w":"23"},"invest-applet.png":{"h":"23","w":"24"},"im-jabber.png":{"h":"24","w":"22"},"logview.png":{"h":"24","w":"20"},"screenie.png":{"h":"24","w":"23"},"xchat-mini.png":{"h":"24","w":"23"},"org.xfce.xfmpc.png":{"h":"24","w":"23"},"palm-pilot.png":{"h":"24","w":"23"},"miro.png":{"h":"21","w":"24"}},"status/24":{"xchat-panel.png":{"h":"24","w":"23"},"process-completed.png":{"h":"16","w":"16"}},"apps/16":{"org.xfce.panel.separator.png":{"h":"22","w":"22"},"gnomine.png":{"h":"13","w":"13"},"gnome-mines.png":{"h":"13","w":"13"}},"animations/22":{"process-working.png":{"h":"330","w":"22"},"gnome-spinner.png":{"h":"330","w":"22"}},"devices/64":{"stock_cell-phone-symbolic.png":{"h":"48","w":"48"},"gnome-phone-manager.png":{"h":"48","w":"48"},"phone.png":{"h":"48","w":"48"},"phone-symbolic.png":{"h":"48","w":"48"},"multimedia-player-ipod-touch.png":{"h":"48","w":"48"},"multimedia-player-apple-ipod-touch.png":{"h":"48","w":"48"},"phone-motorola-droid.png":{"h":"48","w":"48"},"pda.png":{"h":"48","w":"48"},"blueman-smart-phone.png":{"h":"48","w":"48"},"blueman-cellular.png":{"h":"48","w":"48"},"stock_cell-phone.png":{"h":"48","w":"48"},"blueman-handheld.png":{"h":"48","w":"48"}},"animations/32":{"process-working.png":{"h":"480","w":"32"},"gnome-spinner.png":{"h":"480","w":"32"}},"stock/scalable":{"stock_people.svg":{"h":"144","w":"144"},"stock_network-printer.svg":{"h":"144","w":"144"},"stock_new-meeting.svg":{"h":"144","w":"144"},"stock_person.svg":{"h":"144","w":"144"},"stock_person-panel.svg":{"h":"144","w":"144"}},"devices/scalable":{"multimedia-player-apple-ipod-touch.svg":{"h":"48","w":"48"},"phone-motorola-droid.svg":{"h":"48","w":"48"},"pda.svg":{"h":"48","w":"48"},"nm-device-wwan.svg":{"h":"48","w":"48"},"blueman-smart-phone.svg":{"h":"48","w":"48"},"blueman-cellular.svg":{"h":"48","w":"48"},"stock_cell-phone.svg":{"h":"48","w":"48"},"blueman-handheld.svg":{"h":"48","w":"48"},"network-cellular.svg":{"h":"48","w":"48"},"gnome-phone-manager.svg":{"h":"48","w":"48"},"stock_cell-phone-symbolic.svg":{"h":"48","w":"48"},"phone-symbolic.svg":{"h":"48","w":"48"},"multimedia-player-ipod-touch.svg":{"h":"48","w":"48"},"phone.svg":{"h":"48","w":"48"}},"apps/64":{"zorin-connect.png":{"h":"48","w":"48"},"preferences-kde-connect.png":{"h":"48","w":"48"},"kdeconnect.png":{"h":"48","w":"48"}},"devices/48":{"gnome-dev-battery.png":{"h":"48","w":"30"},"audio-speaker-left-back.png":{"h":"68","w":"68"},"audio-speaker-left-back-testing.png":{"h":"68","w":"68"},"audio-speaker-right-back-testing.png":{"h":"68","w":"68"},"battery.png":{"h":"48","w":"30"},"audio-speaker-left.png":{"h":"68","w":"68"},"audio-speaker-right-testing.png":{"h":"68","w":"68"},"audio-speaker-right-back.png":{"h":"68","w":"68"},"audio-speaker-right.png":{"h":"68","w":"68"},"audio-speaker-left-testing.png":{"h":"68","w":"68"}},"emblems/22":{"emblem-colors-orange.png":{"h":"16","w":"16"},"emblem-colors-green.png":{"h":"16","w":"16"},"emblem-colors-yellow.png":{"h":"16","w":"16"},"emblem-colors-violet.png":{"h":"16","w":"16"},"emblem-colors-grey.png":{"h":"16","w":"16"},"emblem-colors-red.png":{"h":"16","w":"16"},"emblem-colors-brown.png":{"h":"16","w":"16"},"emblem-colors-white.png":{"h":"16","w":"16"}},"apps/scalable":{"gnome-do.svg":{"h":"128","w":"128"},"mate-session-properties.svg":{"h":"128","w":"128"},"redshift-status-on.svg":{"h":"48","w":"48"},"do.svg":{"h":"128","w":"128"},"redshift-status-off.svg":{"h":"48","w":"48"},"cs-startup-programs.svg":{"h":"128","w":"128"},"kcmlaunch.svg":{"h":"128","w":"128"},"redshift.svg":{"h":"48","w":"48"},"stock_alarm.svg":{"h":"96","w":"96"},"launch.svg":{"h":"128","w":"128"}},"animations/24":{"process-working.png":{"h":"360","w":"24"},"gnome-spinner.png":{"h":"360","w":"24"}},"status/scalable":{"gnome-netstatus-0-24.svg":{"h":"320","w":"320"},"mail-replied-symbolic.svg":{"h":"96","w":"96"},"aptdaemon-download.svg":{"h":"144","w":"144"},"network-offline.svg":{"h":"144","w":"144"},"network-error.svg":{"h":"144","w":"144"},"update-medium.svg":{"h":"144","w":"144"},"printer-printing.svg":{"h":"144","w":"144"},"battery-low-symbolic.svg":{"h":"96","w":"96"},"weather-fog.svg":{"h":"96","w":"96"},"gnome-netstatus-50-74.svg":{"h":"320","w":"320"},"stock_weather-storm.svg":{"h":"96","w":"96"},"mintupdate-updates-available.svg":{"h":"144","w":"144"},"mail-unread.svg":{"h":"640","w":"640"},"network-wireless-50.svg":{"h":"320","w":"320"},"media-playlist-repeat.svg":{"h":"96","w":"96"},"battery-empty-symbolic.svg":{"h":"96","w":"96"},"dialog-warning.svg":{"h":"96","w":"96"},"battery-good-symbolic.svg":{"h":"96","w":"96"},"battery-level-0.svg":{"h":"96","w":"96"},"weather-clear-night.svg":{"h":"96","w":"96"},"battery-020.svg":{"h":"96","w":"96"},"battery-level-30.svg":{"h":"96","w":"96"},"battery-full-charging.svg":{"h":"96","w":"96"},"media-playlist-shuffle.svg":{"h":"96","w":"96"},"battery-100-charging.svg":{"h":"96","w":"96"},"stock_appointment-reminder.svg":{"h":"96","w":"96"},"stock_lock-open.svg":{"h":"96","w":"96"},"weather-severe-alert.svg":{"h":"96","w":"96"},"network-idle.svg":{"h":"144","w":"144"},"locked.svg":{"h":"96","w":"96"},"stock_dialog-warning.svg":{"h":"96","w":"96"},"wifi-00.svg":{"h":"320","w":"320"},"gtk-connect.svg":{"h":"144","w":"144"},"battery-level-70.svg":{"h":"96","w":"96"},"gnome-netstatus-txrx.svg":{"h":"144","w":"144"},"battery-charged.svg":{"h":"96","w":"96"},"stock_weather-night-few-clouds.svg":{"h":"96","w":"96"},"mintupdate-updates-available-symbolic.svg":{"h":"144","w":"144"},"network-wireless.svg":{"h":"320","w":"320"},"weather-showers-scattered.svg":{"h":"96","w":"96"},"battery_low.svg":{"h":"96","w":"96"},"appointment-soon.svg":{"h":"96","w":"96"},"network-receive.svg":{"h":"144","w":"144"},"gnome-netstatus-tx.svg":{"h":"144","w":"144"},"battery-caution-charging.svg":{"h":"96","w":"96"},"battery-level-100-charged.svg":{"h":"96","w":"96"},"software-update-available.svg":{"h":"144","w":"144"},"task-past-due.svg":{"h":"96","w":"96"},"mail-read.svg":{"h":"96","w":"96"},"network-wireless-00.svg":{"h":"320","w":"320"},"battery_two_thirds.svg":{"h":"96","w":"96"},"appointment-missed.svg":{"h":"96","w":"96"},"security-low.svg":{"h":"96","w":"96"},"network-transmit-receive.svg":{"h":"144","w":"144"},"network-wireless-0.svg":{"h":"320","w":"320"},"stock_connect.svg":{"h":"144","w":"144"},"battery-good-charging.svg":{"h":"96","w":"96"},"battery-level-90-charging.svg":{"h":"96","w":"96"},"battery-empty.svg":{"h":"96","w":"96"},"stock_mail-unread.svg":{"h":"640","w":"640"},"battery-good.svg":{"h":"96","w":"96"},"battery-060.svg":{"h":"96","w":"96"},"battery-level-60-charging.svg":{"h":"96","w":"96"},"stock_weather-cloudy.svg":{"h":"96","w":"96"},"weather-few-clouds.svg":{"h":"96","w":"96"},"network-wireless-75.svg":{"h":"320","w":"320"},"stock_appointment-reminder-excl.svg":{"h":"96","w":"96"},"battery-level-20.svg":{"h":"96","w":"96"},"battery-level-70-charging.svg":{"h":"96","w":"96"},"battery-level-0-symbolic.svg":{"h":"96","w":"96"},"battery-level-30-charging.svg":{"h":"96","w":"96"},"battery_empty.svg":{"h":"96","w":"96"},"gnome-netstatus-error.svg":{"h":"144","w":"144"},"dialog-warning-symbolic.svg":{"h":"96","w":"96"},"network-wireless-25.svg":{"h":"320","w":"320"},"wifi-40.svg":{"h":"320","w":"320"},"security-medium.svg":{"h":"96","w":"96"},"battery-low-charging.svg":{"h":"96","w":"96"},"stock_mail-replied.svg":{"h":"96","w":"96"},"network-wireless-encrypted.svg":{"h":"96","w":"96"},"battery-level-80-charging.svg":{"h":"96","w":"96"},"stock_weather-night-clear.svg":{"h":"96","w":"96"},"update-low.svg":{"h":"144","w":"144"},"battery-level-40-charging.svg":{"h":"96","w":"96"},"battery-level-60.svg":{"h":"96","w":"96"},"stock_weather-snow.svg":{"h":"96","w":"96"},"battery-level-10-charging.svg":{"h":"96","w":"96"},"battery-empty-charging.svg":{"h":"96","w":"96"},"battery-level-50-charging.svg":{"h":"96","w":"96"},"network-wireless-disconnected.svg":{"h":"144","w":"144"},"wifi-80.svg":{"h":"320","w":"320"},"battery_third_fouth.svg":{"h":"96","w":"96"},"battery-level-20-charging.svg":{"h":"96","w":"96"},"gnome-netstatus-25-49.svg":{"h":"320","w":"320"},"battery-caution.svg":{"h":"96","w":"96"},"alarm.svg":{"h":"96","w":"96"},"battery_full.svg":{"h":"96","w":"96"},"dialog-password.svg":{"h":"144","w":"144"},"messagebox_warning.svg":{"h":"96","w":"96"},"battery_third_fourth.svg":{"h":"96","w":"96"},"stock_weather-showers.svg":{"h":"96","w":"96"},"weather-snow.svg":{"h":"96","w":"96"},"battery-low.svg":{"h":"96","w":"96"},"stock_lock.svg":{"h":"96","w":"96"},"network-wireless-connected-50.svg":{"h":"320","w":"320"},"battery-000.svg":{"h":"96","w":"96"},"battery-missing.svg":{"h":"96","w":"96"},"battery-level-10.svg":{"h":"96","w":"96"},"gtk-dialog-authentication.svg":{"h":"144","w":"144"},"sunny.svg":{"h":"96","w":"96"},"network-wireless-connected-00.svg":{"h":"320","w":"320"},"aptdaemon-working.svg":{"h":"144","w":"144"},"battery_charged.svg":{"h":"96","w":"96"},"stock_repeat.svg":{"h":"96","w":"96"},"weather-clear.svg":{"h":"96","w":"96"},"mail-replied.svg":{"h":"96","w":"96"},"weather-storm.svg":{"h":"96","w":"96"},"battery-level-50.svg":{"h":"96","w":"96"},"status_lock.svg":{"h":"96","w":"96"},"connect_no.svg":{"h":"144","w":"144"},"gnome-netstatus-rx.svg":{"h":"144","w":"144"},"stock_lock-broken.svg":{"h":"96","w":"96"},"task-due.svg":{"h":"96","w":"96"},"battery-ac-adapter.svg":{"h":"144","w":"144"},"gnome-netstatus-disconn.svg":{"h":"144","w":"144"},"weather-overcast.svg":{"h":"96","w":"96"},"stock_weather-few-clouds.svg":{"h":"96","w":"96"},"battery-level-0-charging.svg":{"h":"96","w":"96"},"battery-level-100.svg":{"h":"96","w":"96"},"gnome-netstatus-75-100.svg":{"h":"320","w":"320"},"printer-error.svg":{"h":"144","w":"144"},"update-high.svg":{"h":"144","w":"144"},"weather-showers.svg":{"h":"96","w":"96"},"battery-040.svg":{"h":"96","w":"96"},"battery-full.svg":{"h":"96","w":"96"},"mail-attachment.svg":{"h":"96","w":"96"},"connect_creating.svg":{"h":"144","w":"144"},"stock_disconnect.svg":{"h":"144","w":"144"},"wifi-20.svg":{"h":"320","w":"320"},"battery-080.svg":{"h":"96","w":"96"},"battery-level-90.svg":{"h":"96","w":"96"},"stock_mail-open.svg":{"h":"96","w":"96"},"network-transmit.svg":{"h":"144","w":"144"},"network-wireless-connected-75.svg":{"h":"320","w":"320"},"attention.svg":{"h":"96","w":"96"},"battery-080-charging.svg":{"h":"96","w":"96"},"network-wireless-connected-25.svg":{"h":"320","w":"320"},"mail-read-symbolic.svg":{"h":"96","w":"96"},"gnome-netstatus-idle.svg":{"h":"144","w":"144"},"wifi-60.svg":{"h":"320","w":"320"},"software-update-urgent-symbolic.svg":{"h":"144","w":"144"},"battery-full-symbolic.svg":{"h":"96","w":"96"},"battery-060-charging.svg":{"h":"96","w":"96"},"battery_caution.svg":{"h":"96","w":"96"},"battery-020-charging.svg":{"h":"96","w":"96"},"stock_shuffle.svg":{"h":"96","w":"96"},"network-wireless-100.svg":{"h":"320","w":"320"},"wifi-100.svg":{"h":"320","w":"320"},"yum-indicator-info-symbolic.svg":{"h":"144","w":"144"},"gnome-dev-wavelan-encrypted.svg":{"h":"96","w":"96"},"battery-040-charging.svg":{"h":"96","w":"96"},"aptdaemon-add.svg":{"h":"144","w":"144"},"battery-000-charging.svg":{"h":"96","w":"96"},"battery-caution-symbolic.svg":{"h":"96","w":"96"},"battery-level-40.svg":{"h":"96","w":"96"},"gtk-disconnect.svg":{"h":"144","w":"144"},"stock_weather-sunny.svg":{"h":"96","w":"96"},"network-wireless-connected-100.svg":{"h":"320","w":"320"},"security-high.svg":{"h":"96","w":"96"},"battery-full-charged.svg":{"h":"96","w":"96"},"yum-indicator-info.svg":{"h":"144","w":"144"},"stock_attach.svg":{"h":"96","w":"96"},"battery-100.svg":{"h":"96","w":"96"},"weather-few-clouds-night.svg":{"h":"96","w":"96"},"software-update-urgent.svg":{"h":"144","w":"144"},"keys.svg":{"h":"96","w":"96"},"battery-level-80.svg":{"h":"96","w":"96"},"connect_established.svg":{"h":"144","w":"144"},"mail-unread-symbolic.svg":{"h":"640","w":"640"}},"places/scalable":{"bookmark-missing.svg":{"h":"144","w":"144"},"mail-mailbox.svg":{"h":"640","w":"640"},"gnome-fs-bookmark-missing.svg":{"h":"144","w":"144"},"folder-ubuntuone.svg":{"h":"144","w":"144"},"user-bookmarks-symbolic.svg":{"h":"144","w":"144"},"gnome-fs-bookmark.svg":{"h":"144","w":"144"}},"animations/16":{"process-working.png":{"h":"32","w":"80"},"spinner.png":{"h":"160","w":"16"},"gnome-spinner.png":{"h":"32","w":"80"}},"actions/24":{"system-upgrade.png":{"h":"32","w":"32"}}}
